mp3chaps.py
mp3chaps-0.4.dist-info/LICENSE.txt
mp3chaps-0.4.dist-info/METADATA
mp3chaps-0.4.dist-info/WHEEL
mp3chaps-0.4.dist-info/entry_points.txt
mp3chaps-0.4.dist-info/top_level.txt
mp3chaps-0.4.dist-info/RECORD
