Metadata-Version: 2.1
Name: mp3chaps
Version: 0.4
Summary: tool for inserting chapter marks in mp3 files
Home-page: https://github.com/dskrad/mp3chaps
Author: David Karimeddini
Author-email: dskcl1@gmail.com
License: MIT
Keywords: mp3 chapters
Platform: UNKNOWN
Classifier: License :: OSI Approved :: MIT License
Classifier: Programming Language :: Python
Classifier: Programming Language :: Python :: 3
Classifier: Programming Language :: Python :: 3.3
Classifier: Programming Language :: Python :: 3.4
Classifier: Programming Language :: Python :: 3.5
Classifier: Programming Language :: Python :: 3.6
Classifier: Programming Language :: Python :: Implementation :: CPython
Classifier: Programming Language :: Python :: Implementation :: PyPy
Requires-Dist: docopt (>=0.6.2)
Requires-Dist: eyeD3 (>=0.9.5)
